{
  "topic": "dmg",
  "condition": "bear",
  "started": "2026-04-11 04:40:56",
  "last_updated": "2026-04-11 04:44:55",
  "elapsed_seconds": 238.3,
  "n_turns": 24,
  "n_pdfs_ingested": 2,
  "n_diffusion_stored": 32,
  "n_diffusion_skipped": 14,
  "ingestions": [
    {
      "time": "04:42:11",
      "turn": 7,
      "hat": "White",
      "title": "Liu%20et%20al%20adaptive%20immunotherapeutic%20paradigms%20in%20DMG",
      "chunks": 54
    },
    {
      "time": "04:44:04",
      "turn": 18,
      "hat": "White",
      "title": "Nonnenbroich%20DMG%20from%20molecular%20mechanisms%20to%20targeted%20interventions",
      "chunks": 41
    }
  ],
  "log_path": "/mnt/c/Users/Scott/Documents/Work/bear/examples/bear_parlor/session_logs/brainstorming-hats_20260411_044056.md",
  "completed": true,
  "ended": "2026-04-11 04:45:03",
  "duration_seconds": 246.8
}